p_stable_lsh/__init__.py
p_stable_lsh/pstable.py
p_stable_lsh_python-0.0.3.dist-info/LICENSE
p_stable_lsh_python-0.0.3.dist-info/METADATA
p_stable_lsh_python-0.0.3.dist-info/WHEEL
p_stable_lsh_python-0.0.3.dist-info/top_level.txt
p_stable_lsh_python-0.0.3.dist-info/RECORD
