Metadata-Version: 2.1
Name: p-stable-lsh-python
Version: 0.0.3
Summary: A 1&2-stable Locality-Sensitive Hashing implementation in Python
Home-page: https://github.com/CharlesLiu7/p-stable-lsh-python
Author: Charles7
Author-email: liuhuiqi@mail.ustc.edu.cn
License: UNKNOWN
Project-URL: Bug Tracker, https://github.com/CharlesLiu7/p-stable-lsh-python/issues
Platform: UNKNOWN
Classifier: Programming Language :: Python :: 3
Classifier: License :: OSI Approved :: MIT License
Classifier: Operating System :: OS Independent
Requires-Python: >=3.6
License-File: LICENSE
Requires-Dist: numpy
Requires-Dist: scipy
